DEA/DEA.py
DEA/__init__.py
DEA-0.2.dist-info/LICENSE
DEA-0.2.dist-info/METADATA
DEA-0.2.dist-info/WHEEL
DEA-0.2.dist-info/top_level.txt
DEA-0.2.dist-info/RECORD
