Metadata-Version: 2.1
Name: DEA
Version: 0.2
Summary: A simple library for differential expression analysis
Home-page: https://github.com/jeffliu6068/DEA
Author: Jeff Liu
Author-email: jeffliu6068@gmail.com
License: LICENSE.txt
Platform: UNKNOWN
Requires-Dist: pandas
Requires-Dist: scipy
Requires-Dist: numpy
Requires-Dist: matplotlib
Requires-Dist: sklearn
Requires-Dist: tqdm
